{
  "plugins": {
    "blink.cmp": {
      "rev": "327fff9",
      "src": "https://github.com/Saghen/blink.cmp",
      "version": ">=0.0.0"
    },
    "ccc.nvim": [],
    "conform.nvim": {
      "rev": "9fd3d5e",
      "src": "https://github.com/stevearc/conform.nvim"
    },
    "floaterm": {
      "rev": "34e14f0",
      "src": "https://github.com/nvzone/floaterm"
    },
    "fzf-lua": {
      "rev": "a8458b7",
      "src": "https://github.com/ibhagwan/fzf-lua"
    },
    "kanagawa.nvim": {
      "rev": "aef7f5c",
      "src": "https://github.com/rebelot/kanagawa.nvim"
    },
    "lazydev.nvim": {
      "rev": "c2dfe35",
      "src": "https://github.com/folke/lazydev.nvim"
    },
    "mini.surround": {
      "rev": "3c73e2a",
      "src": "https://github.com/nvim-mini/mini.surround"
    },
    "nvim-dap": {
      "rev": "6782b09",
      "src": "https://github.com/mfussenegger/nvim-dap"
    },
    "nvim-dap-view": {
      "rev": "1fe98bc",
      "src": "https://github.com/igorlfs/nvim-dap-view"
    },
    "nvim-lspconfig": {
      "rev": "87d3018",
      "src": "https://github.com/neovim/nvim-lspconfig"
    },
    "nvim-treesitter": {
      "rev": "42fc28ba",
      "src": "https://github.com/nvim-treesitter/nvim-treesitter"
    },
    "nvim-web-devicons": {
      "rev": "8dcb311",
      "src": "https://github.com/nvim-tree/nvim-web-devicons"
    },
    "oil.nvim": {
      "rev": "7e1cd77",
      "src": "https://github.com/stevearc/oil.nvim"
    },
    "rustaceanvim": {
      "rev": "be0d1d1",
      "src": "https://github.com/mrcjkb/rustaceanvim"
    },
    "volt": {
      "rev": "620de13",
      "src": "https://github.com/nvzone/volt"
    }
  }
}